genetest/__init__.py
genetest/analysis.py
genetest/configuration.py
genetest/subscribers.py
genetest/version.py
genetest/modelspec/__init__.py
genetest/modelspec/core.py
genetest/modelspec/grammar.py
genetest/modelspec/modelspec.ebnf
genetest/modelspec/parser.py
genetest/modelspec/predicates.py
genetest/phenotypes/__init__.py
genetest/phenotypes/core.py
genetest/phenotypes/dataframe.py
genetest/phenotypes/dummy.py
genetest/phenotypes/text.py
genetest/scripts/__init__.py
genetest/scripts/cli.py
genetest/scripts/convert.py
genetest/statistics/__init__.py
genetest/statistics/core.py
genetest/statistics/descriptive.py
genetest/statistics/models/__init__.py
genetest/statistics/models/linear.py
genetest/statistics/models/logistic.py
genetest/statistics/models/mixedlm.py
genetest/statistics/models/skat.py
genetest/statistics/models/survival.py
genetest/tests/__init__.py
genetest/tests/__main__.py
genetest/tests/test_configuration.py
genetest/tests/test_coxph.py
genetest/tests/test_descriptive_stats.py
genetest/tests/test_grammar.py
genetest/tests/test_gwaswriter.py
genetest/tests/test_linear.py
genetest/tests/test_logistic.py
genetest/tests/test_mixedlm.py
genetest/tests/test_modelspec.py
genetest/tests/test_phenotypes.py
genetest/tests/test_stats_core.py
genetest/tests/data/genotypes/input.vcf.gz
genetest/tests/data/genotypes/input.vcf.gz.tbi
genetest/tests/data/statistics/coxph.txt.bz2
genetest/tests/data/statistics/factors.txt.bz2
genetest/tests/data/statistics/linear.txt.bz2
genetest/tests/data/statistics/linear_missing.txt.bz2
genetest/tests/data/statistics/logistic.txt.bz2
genetest/tests/data/statistics/logistic_missing.txt.bz2
genetest/tests/data/statistics/mixedlm.txt.bz2
genetest-0.6.0.dist-info/LICENSE.txt
genetest-0.6.0.dist-info/METADATA
genetest-0.6.0.dist-info/WHEEL
genetest-0.6.0.dist-info/entry_points.txt
genetest-0.6.0.dist-info/top_level.txt
genetest-0.6.0.dist-info/RECORD
