Metadata-Version: 2.1
Name: genetest
Version: 0.6.0
Summary: A package to process and analyze genotypic and phenotypic data.
Home-page: https://github.com/pgxcentre/genetest
License: CC BY-NC 4.0
Keywords: bioinformatics genetics statistics
Platform: UNKNOWN
Classifier: Development Status :: 4 - Beta
Classifier: Intended Audience :: Science/Research
Classifier: License :: Free for non-commercial use
Classifier: Operating System :: Unix
Classifier: Operating System :: POSIX :: Linux
Classifier: Operating System :: MacOS :: MacOS X
Classifier: Operating System :: Microsoft
Classifier: Programming Language :: Python
Classifier: Programming Language :: Python :: 3.4
Classifier: Programming Language :: Python :: 3.5
Classifier: Programming Language :: Python :: 3.6
Classifier: Topic :: Scientific/Engineering :: Bio-Informatics
License-File: LICENSE.txt
Requires-Dist: numpy (>=1.12.0)
Requires-Dist: pandas (>=0.19.0)
Requires-Dist: setuptools (>=26.1.0)
Requires-Dist: statsmodels (>=0.8.0)
Requires-Dist: grako (>=3.10.0)
Requires-Dist: scipy (>=0.19.0)
Requires-Dist: geneparse (>=0.4.1)
Requires-Dist: pyyaml (>=3.12)
